skqulacs/__init__.py
skqulacs/circuit/__init__.py
skqulacs/circuit/circuit.py
skqulacs/circuit/pre_defined.py
skqulacs/dataloader.py
skqulacs/qkrr/__init__.py
skqulacs/qkrr/qkrr.py
skqulacs/qnn/__init__.py
skqulacs/qnn/classifier.py
skqulacs/qnn/generation.py
skqulacs/qnn/regressor.py
skqulacs/qnn/solver.py
skqulacs/qsvm/__init__.py
skqulacs/qsvm/qsvc.py
skqulacs/qsvm/qsvr.py
skqulacs/save.py
skqulacs-0.5.3.dist-info/LICENSE
skqulacs-0.5.3.dist-info/METADATA
skqulacs-0.5.3.dist-info/WHEEL
skqulacs-0.5.3.dist-info/RECORD
