Metadata-Version: 2.3
Name: skqulacs
Version: 0.5.3
Summary: scikit-qulacs is a library for quantum neural network. This library is based on qulacs and named after scikit-learn.
License: MIT
Author: Qulacs-Osaka
Author-email: qulacs.osaka@gmail.com
Requires-Python: >=3.9
Classifier: Development Status :: 3 - Alpha
Classifier: Intended Audience :: Science/Research
Classifier: License :: OSI Approved :: MIT License
Classifier: Operating System :: MacOS
Classifier: Operating System :: Microsoft :: Windows
Classifier: Operating System :: POSIX :: Linux
Classifier: Programming Language :: Python
Classifier: Programming Language :: Python :: 3
Classifier: Programming Language :: Python :: 3.9
Classifier: Programming Language :: Python :: 3.10
Classifier: Programming Language :: Python :: 3.11
Classifier: Programming Language :: Python :: 3.12
Classifier: Programming Language :: Python :: 3.13
Classifier: Topic :: Scientific/Engineering :: Physics
Requires-Dist: numpy (>=1.24.0,<2.0.0)
Requires-Dist: qulacs (>=0.5.0)
Requires-Dist: scikit-learn (>=1.0.0,<2.0.0)
Requires-Dist: scipy (>=1.10.0)
Requires-Dist: typing-extensions (>=4.3.0,<5.0.0)
Project-URL: Documentation, https://qulacs-osaka.github.io/scikit-qulacs/index.html
Project-URL: Homepage, https://github.com/Qulacs-Osaka/scikit-qulacs
Project-URL: Repository, https://github.com/Qulacs-Osaka/scikit-qulacs
